chunckerflow-0.1.0.dist-info/licenses/LICENSE
chunk_flow/__init__.py
chunk_flow/analysis/__init__.py
chunk_flow/analysis/results_dataframe.py
chunk_flow/analysis/visualization.py
chunk_flow/api/__init__.py
chunk_flow/api/app.py
chunk_flow/api/models.py
chunk_flow/chunking/__init__.py
chunk_flow/chunking/registry.py
chunk_flow/chunking/strategies/__init__.py
chunk_flow/chunking/strategies/document_based.py
chunk_flow/chunking/strategies/fixed_size.py
chunk_flow/chunking/strategies/late.py
chunk_flow/chunking/strategies/recursive.py
chunk_flow/chunking/strategies/semantic.py
chunk_flow/core/__init__.py
chunk_flow/core/base.py
chunk_flow/core/config.py
chunk_flow/core/exceptions.py
chunk_flow/core/models.py
chunk_flow/core/version.py
chunk_flow/embeddings/__init__.py
chunk_flow/embeddings/factory.py
chunk_flow/embeddings/providers/__init__.py
chunk_flow/embeddings/providers/huggingface_provider.py
chunk_flow/embeddings/providers/openai_provider.py
chunk_flow/evaluation/__init__.py
chunk_flow/evaluation/comparison.py
chunk_flow/evaluation/pipeline.py
chunk_flow/evaluation/registry.py
chunk_flow/evaluation/metrics/__init__.py
chunk_flow/evaluation/metrics/rag_quality.py
chunk_flow/evaluation/metrics/retrieval.py
chunk_flow/evaluation/metrics/semantic.py
chunk_flow/results/__init__.py
chunk_flow/utils/__init__.py
chunk_flow/utils/async_helpers.py
chunk_flow/utils/logging.py
chunckerflow-0.1.0.dist-info/METADATA
chunckerflow-0.1.0.dist-info/WHEEL
chunckerflow-0.1.0.dist-info/top_level.txt
chunckerflow-0.1.0.dist-info/RECORD
