Metadata-Version: 2.4
Name: chunckerflow
Version: 0.1.0
Summary: Production-grade async text chunking framework for RAG systems
Author: ChunkFlow Contributors
License: MIT
Project-URL: Homepage, https://github.com/guybass/chunckerflow
Project-URL: Documentation, https://github.com/guybass/chunckerflow
Project-URL: Repository, https://github.com/guybass/chunckerflow
Project-URL: Issues, https://github.com/guybass/chunckerflow/issues
Keywords: chunking,rag,retrieval,embeddings,nlp,text-processing,semantic-search
Classifier: Development Status :: 3 - Alpha
Classifier: Intended Audience :: Developers
Classifier: Intended Audience :: Science/Research
Classifier: License :: OSI Approved :: MIT License
Classifier: Programming Language :: Python :: 3
Classifier: Programming Language :: Python :: 3.9
Classifier: Programming Language :: Python :: 3.10
Classifier: Programming Language :: Python :: 3.11
Classifier: Programming Language :: Python :: 3.12
Classifier: Topic :: Scientific/Engineering :: Artificial Intelligence
Classifier: Topic :: Text Processing
Requires-Python: >=3.9
License-File: LICENSE
Requires-Dist: pydantic>=2.0.0
Requires-Dist: pydantic-settings>=2.0.0
Requires-Dist: numpy>=1.24.0
Requires-Dist: pandas>=2.0.0
Requires-Dist: pyarrow>=12.0.0
Requires-Dist: httpx>=0.24.0
Requires-Dist: tenacity>=8.2.0
Requires-Dist: structlog>=23.1.0
Requires-Dist: python-dotenv>=1.0.0
Requires-Dist: tiktoken>=0.5.0
Requires-Dist: scikit-learn>=1.3.0
Requires-Dist: scipy>=1.11.0
Provides-Extra: api
Requires-Dist: fastapi>=0.104.0; extra == "api"
Requires-Dist: uvicorn[standard]>=0.24.0; extra == "api"
Provides-Extra: openai
Requires-Dist: openai>=1.0.0; extra == "openai"
Provides-Extra: huggingface
Requires-Dist: sentence-transformers>=2.2.0; extra == "huggingface"
Requires-Dist: transformers>=4.30.0; extra == "huggingface"
Requires-Dist: torch>=2.0.0; extra == "huggingface"
Provides-Extra: google
Requires-Dist: google-cloud-aiplatform>=1.38.0; extra == "google"
Provides-Extra: cohere
Requires-Dist: cohere>=4.0.0; extra == "cohere"
Provides-Extra: viz
Requires-Dist: matplotlib>=3.7.0; extra == "viz"
Requires-Dist: seaborn>=0.12.0; extra == "viz"
Requires-Dist: plotly>=5.14.0; extra == "viz"
Requires-Dist: streamlit>=1.28.0; extra == "viz"
Provides-Extra: dev
Requires-Dist: pytest>=7.4.0; extra == "dev"
Requires-Dist: pytest-asyncio>=0.21.0; extra == "dev"
Requires-Dist: pytest-cov>=4.1.0; extra == "dev"
Requires-Dist: pytest-mock>=3.11.0; extra == "dev"
Requires-Dist: black>=23.0.0; extra == "dev"
Requires-Dist: ruff>=0.1.0; extra == "dev"
Requires-Dist: isort>=5.12.0; extra == "dev"
Requires-Dist: mypy>=1.6.0; extra == "dev"
Requires-Dist: pre-commit>=3.5.0; extra == "dev"
Requires-Dist: ipython>=8.12.0; extra == "dev"
Provides-Extra: all
Requires-Dist: chunckerflow[api,cohere,dev,google,huggingface,openai,viz]; extra == "all"
Dynamic: license-file
